embed4d/__init__.py
embed4d/utilities.py
embed4d/viewer.py
embed4d/viewer_server.py
embed4d/templates/fbx_loader.html
embed4d/templates/index.html
embed4d/templates/loader.html
embed4d/templates/loader2.html
embed4d/templates/video.html
embed4d-0.0.4.dist-info/licenses/LICENSE
embed4d-0.0.4.dist-info/METADATA
embed4d-0.0.4.dist-info/WHEEL
embed4d-0.0.4.dist-info/top_level.txt
embed4d-0.0.4.dist-info/RECORD
