Metadata-Version: 2.4
Name: embed4d
Version: 0.0.4
Summary: Embed 4D (3D + time): lightweight GLB/GLTF/FBX animation viewer (standalone HTML + Python helpers for embedding/export).
Author: MyoLab, Inc.
Maintainer-email: Vittorio Caggiano <caggiano@gmail.com>
License:                                  Apache License
Keywords: threejs,gltf,glb,viewer,animation,gradio,embed
Classifier: Development Status :: 3 - Alpha
Classifier: Programming Language :: Python :: 3
Classifier: Programming Language :: Python :: 3 :: Only
Classifier: License :: Other/Proprietary License
Classifier: Operating System :: OS Independent
Requires-Python: >=3.10
License-File: LICENSE
Requires-Dist: pywebview
Requires-Dist: fastapi
Requires-Dist: uvicorn
Provides-Extra: test
Requires-Dist: pytest; extra == "test"
Requires-Dist: gradio>=5.25; extra == "test"
Provides-Extra: gradio
Requires-Dist: gradio>=5.25; extra == "gradio"
Provides-Extra: ipython
Requires-Dist: ipython; extra == "ipython"
Provides-Extra: dev
Requires-Dist: pre-commit; extra == "dev"
Requires-Dist: pytest; extra == "dev"
Requires-Dist: ipython; extra == "dev"
Requires-Dist: gradio; extra == "dev"
Dynamic: license-file
